pylynkz/__init__.py
pylynkz/logger.py
pylynkz-0.0.3.dist-info/LICENSE.txt
pylynkz-0.0.3.dist-info/METADATA
pylynkz-0.0.3.dist-info/WHEEL
pylynkz-0.0.3.dist-info/top_level.txt
pylynkz-0.0.3.dist-info/RECORD
