Metadata-Version: 2.1
Name: pylynkz
Version: 0.0.3
Summary: Testing installation of Package
Home-page: https://github.com/Lynkz-Instruments/pylynkz
Author: Alexandre Desgagné
Author-email: alexd@lynkz.ca
License: MIT
Classifier: Development Status :: 3 - Alpha
Classifier: Intended Audience :: Developers
License-File: LICENSE.txt
Requires-Dist: requests
Requires-Dist: termcolor
Requires-Dist: colorama (>=0.4.6)
